google_spreadsheets_exporter/__init__.py
google_spreadsheets_exporter/exporter.py
google_spreadsheets_exporter/utils.py
google_spreadsheets_exporter-1.0.5.dist-info/LICENSE
google_spreadsheets_exporter-1.0.5.dist-info/METADATA
google_spreadsheets_exporter-1.0.5.dist-info/WHEEL
google_spreadsheets_exporter-1.0.5.dist-info/top_level.txt
google_spreadsheets_exporter-1.0.5.dist-info/RECORD
