Metadata-Version: 2.1
Name: google-spreadsheets-exporter
Version: 1.0.5
License-File: LICENSE
Requires-Dist: google-api-python-client
Requires-Dist: google-auth-httplib2
Requires-Dist: google-auth-oauthlib
